Metadata-Version: 2.1
Name: hpapi
Version: 0.0.3
Summary: hpapi is a Python package for discovering and interacting with HP printers on the network. It allows users to discover printers, check their scanning status, and initiate scans. Please note that this package is not affiliated with HP and is an independent project.
